solapi/__init__.py
solapi/error/MessageNotReceiveError.py
solapi/lib/__init__.py
solapi/lib/authenticator.py
solapi/lib/fetcher.py
solapi/lib/string_date_transfer.py
solapi/model/__init__.py
solapi/model/message_type.py
solapi/model/kakao/__init__.py
solapi/model/kakao/kakao_button.py
solapi/model/kakao/kakao_option.py
solapi/model/naver/naver_button.py
solapi/model/naver/naver_option.py
solapi/model/rcs/__init__.py
solapi/model/rcs/rcs_options.py
solapi/model/request/__init__.py
solapi/model/request/message.py
solapi/model/request/send_message_request.py
solapi/model/request/storage.py
solapi/model/request/groups/get_groups.py
solapi/model/request/kakao/bms.py
solapi/model/request/kakao/kakao_option.py
solapi/model/request/messages/get_messages.py
solapi/model/request/voice/voice_option.py
solapi/model/response/__init__.py
solapi/model/response/common_response.py
solapi/model/response/message.py
solapi/model/response/send_message_response.py
solapi/model/response/storage.py
solapi/model/response/balance/get_balance.py
solapi/model/response/groups/get_group_messages.py
solapi/model/response/groups/get_groups.py
solapi/model/response/messages/get_messages.py
solapi/model/webhook/group_report.py
solapi/model/webhook/single_report.py
solapi/services/__init__.py
solapi/services/message_service.py
solapi-5.0.2.dist-info/METADATA
solapi-5.0.2.dist-info/WHEEL
solapi-5.0.2.dist-info/licenses/LICENSE
solapi-5.0.2.dist-info/RECORD
